kubernetes/__init__.py
kubernetes/client/__init__.py
kubernetes/client/api_client.py
kubernetes/client/configuration.py
kubernetes/client/rest.py
kubernetes/client/apis/__init__.py
kubernetes/client/apis/admissionregistration_api.py
kubernetes/client/apis/admissionregistration_v1alpha1_api.py
kubernetes/client/apis/apiextensions_api.py
kubernetes/client/apis/apiextensions_v1beta1_api.py
kubernetes/client/apis/apiregistration_api.py
kubernetes/client/apis/apiregistration_v1beta1_api.py
kubernetes/client/apis/apis_api.py
kubernetes/client/apis/apps_api.py
kubernetes/client/apis/apps_v1beta1_api.py
kubernetes/client/apis/apps_v1beta2_api.py
kubernetes/client/apis/authentication_api.py
kubernetes/client/apis/authentication_v1_api.py
kubernetes/client/apis/authentication_v1beta1_api.py
kubernetes/client/apis/authorization_api.py
kubernetes/client/apis/authorization_v1_api.py
kubernetes/client/apis/authorization_v1beta1_api.py
kubernetes/client/apis/autoscaling_api.py
kubernetes/client/apis/autoscaling_v1_api.py
kubernetes/client/apis/autoscaling_v2beta1_api.py
kubernetes/client/apis/batch_api.py
kubernetes/client/apis/batch_v1_api.py
kubernetes/client/apis/batch_v1beta1_api.py
kubernetes/client/apis/batch_v2alpha1_api.py
kubernetes/client/apis/certificates_api.py
kubernetes/client/apis/certificates_v1beta1_api.py
kubernetes/client/apis/core_api.py
kubernetes/client/apis/core_v1_api.py
kubernetes/client/apis/custom_objects_api.py
kubernetes/client/apis/extensions_api.py
kubernetes/client/apis/extensions_v1beta1_api.py
kubernetes/client/apis/logs_api.py
kubernetes/client/apis/networking_api.py
kubernetes/client/apis/networking_v1_api.py
kubernetes/client/apis/policy_api.py
kubernetes/client/apis/policy_v1beta1_api.py
kubernetes/client/apis/rbac_authorization_api.py
kubernetes/client/apis/rbac_authorization_v1_api.py
kubernetes/client/apis/rbac_authorization_v1alpha1_api.py
kubernetes_async_patch-4.0.1.dist-info/METADATA
kubernetes_async_patch-4.0.1.dist-info/RECORD
kubernetes_async_patch-4.0.1.dist-info/WHEEL
kubernetes_async_patch-4.0.1.dist-info/top_level.txt
